juchats/__init__.py
juchats/chat.py
juchats/configs.py
juchats/models.py
juchats/openai.py
juchats/types.py
juchats-0.0.3.dist-info/METADATA
juchats-0.0.3.dist-info/WHEEL
juchats-0.0.3.dist-info/RECORD
