Metadata-Version: 2.1
Name: juchats
Version: 0.0.3
Summary: 
Author: ultrasev
Author-email: i@ultrasev.com
Requires-Python: >=3.8,<4.0
Classifier: Programming Language :: Python :: 3
Classifier: Programming Language :: Python :: 3.8
Classifier: Programming Language :: Python :: 3.9
Classifier: Programming Language :: Python :: 3.10
Classifier: Programming Language :: Python :: 3.11
Classifier: Programming Language :: Python :: 3.12
Requires-Dist: fastapi (>=0.112.1,<0.113.0)
Requires-Dist: httpx (>=0.27.0,<0.28.0)
Requires-Dist: loguru (>=0.7.2,<0.8.0)
Requires-Dist: pydantic (>=2.8.2,<3.0.0)
Requires-Dist: redislite (>=6.2.912183,<7.0.0)
Requires-Dist: uuid (>=1.30,<2.0)
Requires-Dist: uvicorn (>=0.30.6,<0.31.0)
Requires-Dist: websockets (>=12.0,<13.0)
